setup.py
Semicolonizer/Semicolonizer.py
Semicolonizer/__init__.py
Semicolonizer.egg-info/PKG-INFO
Semicolonizer.egg-info/SOURCES.txt
Semicolonizer.egg-info/dependency_links.txt
Semicolonizer.egg-info/requires.txt
Semicolonizer.egg-info/top_level.txt