Metadata-Version: 2.1
Name: Semicolonizer
Version: 1.2
Summary: a tool for semicolonize php files!
Home-page: 
Author: Mobin
Author-email: 12345mobin12345@gmail.com
License: MIT
